pool_workers/__init__.py
pool_workers-0.0.6.dist-info/LICENSE
pool_workers-0.0.6.dist-info/METADATA
pool_workers-0.0.6.dist-info/WHEEL
pool_workers-0.0.6.dist-info/RECORD
