Metadata-Version: 2.1
Name: pool-workers
Version: 0.0.6
Summary: pool-workers is a light weight package for dealing & managing pools, workers and queues.
Home-page: https://github.com/medram/pool_workers
License: MIT
Keywords: threads,pools,threading,queue,pool-workers
Author: medram
Author-email: mramouchy@gmail.com
Requires-Python: >=3.9,<4.0
Classifier: License :: OSI Approved :: MIT License
Classifier: Operating System :: OS Independent
Classifier: Programming Language :: Python :: 3
Classifier: Programming Language :: Python :: 3.9
Classifier: Programming Language :: Python :: 3.10
Classifier: Programming Language :: Python :: 3.11
Classifier: Programming Language :: Python :: 3.12
Classifier: Programming Language :: Python :: 3.7
Requires-Dist: pydantic (>=2.5.3,<3.0.0)
Project-URL: Documentation, https://github.com/medram/pool_workers
Project-URL: Repository, https://github.com/medram/pool_workers
